{
  "_comment": "[CI-LOCKED] The content of this file is locked. Contributions are welcome, but change validation may be delayed.",
  "ACTIVITY_BOT_SAID": "Bot $1 said, $2. Sent at $3.",
  "ACTIVITY_ERROR_BOX_TITLE": "Mensagem de erro",
  "ACTIVITY_STATUS_SEND_FAILED_RETRY": "Falha ao enviar. [Repetir][RETRY].",
  "ACTIVITY_STATUS_SEND_STATUS_ALT_SENDING": "A enviar",
  "ACTIVITY_STATUS_SEND_STATUS_ALT_SENT_AT": "Enviado às $1",
  "ACTIVITY_STATUS_SEND_STATUS_ALT": "Estado do Envio: $1",
  "ACTIVITY_STATUS_TIMESTAMP_JUST_NOW": "Agora mesmo",
  "ACTIVITY_STATUS_TIMESTAMP_ONE_HOUR_AGO": "Há uma hora",
  "ACTIVITY_STATUS_TIMESTAMP_ONE_MINUTE_AGO": "Há um minuto",
  "ACTIVITY_STATUS_TIMESTAMP_TODAY": "Today",
  "ACTIVITY_STATUS_TIMESTAMP_YESTERDAY": "Yesterday",
  "ACTIVITY_USER_SAID": "User $1 said, $2. Sent at $3.",
  "ADAPTIVE_CARD_ERROR_BOX_TITLE_PARSE": "Erro de análise de Cartão Adaptável",
  "ADAPTIVE_CARD_ERROR_BOX_TITLE_RENDER": "Erro de composição de Cartão Adaptável",
  "CAROUSEL_ATTACHMENTS_BOT_ALT": "Enviado pelo bot",
  "CAROUSEL_ATTACHMENTS_USER_ALT": "Enviado pelo utilizador",
  "CAROUSEL_FLIPPER_LEFT_ALT": "Esquerda",
  "CAROUSEL_FLIPPER_RIGHT_ALT": "Direita",
  "CONNECTIVITY_STATUS_ALT_CONNECTED": "Ligado",
  "CONNECTIVITY_STATUS_ALT_CONNECTING": "A ligar…",
  "CONNECTIVITY_STATUS_ALT_FATAL": "Não é possível ligar.",
  "CONNECTIVITY_STATUS_ALT_RECONNECTING": "Ocorreu uma interrupção de rede. A restabelecer ligação…",
  "CONNECTIVITY_STATUS_ALT_RENDER_ERROR": "Erro de composição. Verifique a consola ou contacte o programador do bot.",
  "CONNECTIVITY_STATUS_ALT_SLOW_CONNECTION": "O estabelecimento da ligação está a demorar mais tempo do que o esperado.",
  "CONNECTIVITY_STATUS_ALT": "Estado de Conectividade: $1",
  "FILE_CONTENT_ALT": "'$1'",
  "FILE_CONTENT_DOWNLOADABLE_ALT": "Download file '$1'",
  "FILE_CONTENT_DOWNLOADABLE_WITH_SIZE_ALT": "Download file '$1' of size $2",
  "FILE_CONTENT_WITH_SIZE_ALT": "'$1' of size $2",
  "RECEIPT_CARD_TAX": "Imposto",
  "RECEIPT_CARD_TOTAL": "Total",
  "RECEIPT_CARD_VAT": "IVA",
  "SPEECH_INPUT_LISTENING": "A escutar…",
  "SPEECH_INPUT_MICROPHONE_BUTTON_CLOSE_ALT": "Microfone desativado",
  "SPEECH_INPUT_MICROPHONE_BUTTON_OPEN_ALT": "Microfone ativado",
  "SPEECH_INPUT_STARTING": "A iniciar…",
  "SUGGESTED_ACTIONS_ALT_HAS_CONTENT": "Tem conteúdo",
  "SUGGESTED_ACTIONS_ALT_NO_CONTENT": "Está vazio",
  "SUGGESTED_ACTIONS_ALT": "Contentor de Ações Sugeridas: $1",
  "TEXT_INPUT_ALT": "Caixa de entrada de mensagens",
  "TEXT_INPUT_PLACEHOLDER": "Escreva a sua mensagem",
  "TEXT_INPUT_SEND_BUTTON_ALT": "Enviar",
  "TEXT_INPUT_SPEAK_BUTTON_ALT": "Falar",
  "TEXT_INPUT_UPLOAD_BUTTON_ALT": "Upload file",
  "TOAST_ACCORDION_FEW": "$1 Notifications: Click here to see details",
  "TOAST_ACCORDION_MANY": "$1 Notifications: Click here to see details",
  "TOAST_ACCORDION_OTHER": "$1 Notifications: Click here to see details",
  "TOAST_ACCORDION_TWO": "$1 Notifications: Click here to see details",
  "TOAST_ALT_ERROR": "Error",
  "TOAST_ALT_INFO": "Information",
  "TOAST_ALT_SUCCESS": "Success",
  "TOAST_ALT_WARN": "Warning",
  "TOAST_DISMISS_BUTTON": "Dismiss",
  "TOAST_TITLE_ALT": "Notification",
  "TRANSCRIPT_NEW_MESSAGES": "Novas mensagens",
  "TYPING_INDICATOR_ALT": "A mostrar o indicador de escrita"
}